streamwish/__init__.py
streamwish/auctioneer.py
streamwish/distiller.py
streamwish/graph_engine.py
streamwish/ingestion.py
streamwish/llm_interface.py
streamwish/manager.py
streamwish-0.1.2.dist-info/licenses/LICENSE
streamwish-0.1.2.dist-info/METADATA
streamwish-0.1.2.dist-info/WHEEL
streamwish-0.1.2.dist-info/top_level.txt
streamwish-0.1.2.dist-info/RECORD
