Metadata-Version: 2.4
Name: streamwish
Version: 0.1.2
Summary: StreamWish: A Retrieval-Augmented Generation (RAG) library optimized for small context windows using graph traversal.
Author-email: Vishnu Kumar <vishnukumar.annamalai@gmail.com>
License: MIT
Project-URL: Homepage, https://github.com/vichu3d-dev/streamwishrepo
Project-URL: Bug Tracker, https://github.com/vichu3d-dev/streamwishrepo/issues
Keywords: rag,llm,graph,ai,streaming
Classifier: Development Status :: 3 - Alpha
Classifier: Intended Audience :: Developers
Classifier: License :: OSI Approved :: MIT License
Classifier: Programming Language :: Python :: 3
Requires-Python: >=3.8
License-File: LICENSE
Requires-Dist: networkx>=3.0
Requires-Dist: pydantic>=2.0
Requires-Dist: numpy>=1.24.0
Requires-Dist: openai>=1.0.0
Requires-Dist: pandas>=2.0.0
Requires-Dist: openpyxl>=3.1.0
Requires-Dist: pypdf>=3.0.0
Requires-Dist: google-api-python-client>=2.0.0
Requires-Dist: google-auth>=2.0.0
Dynamic: license-file
